factorial_aio/__init__.py
factorial_aio/app.py
factorial_aio/factorial.py
factorial_aio-0.1.0.dist-info/METADATA
factorial_aio-0.1.0.dist-info/WHEEL
factorial_aio-0.1.0.dist-info/RECORD
